AUTHORS
CHANGELOG
CHANGES.txt
LICENSE
MANIFEST.in
README
README.rst
README_RUS.rst
setup.py
autocomplete_light/__init__.py
autocomplete_light/apps.py
autocomplete_light/exceptions.py
autocomplete_light/fields.py
autocomplete_light/forms.py
autocomplete_light/generic.py
autocomplete_light/models.py
autocomplete_light/registry.py
autocomplete_light/settings.py
autocomplete_light/urls.py
autocomplete_light/views.py
autocomplete_light/widgets.py
autocomplete_light/autocomplete/__init__.py
autocomplete_light/autocomplete/base.py
autocomplete_light/autocomplete/choice_list.py
autocomplete_light/autocomplete/generic.py
autocomplete_light/autocomplete/html.py
autocomplete_light/autocomplete/list.py
autocomplete_light/autocomplete/model.py
autocomplete_light/autocomplete/rest_model.py
autocomplete_light/autocomplete/template.py
autocomplete_light/contrib/__init__.py
autocomplete_light/contrib/hvad.py
autocomplete_light/contrib/taggit_field.py
autocomplete_light/example_apps/__init__.py
autocomplete_light/example_apps/autocomplete_test_case_app/__init__.py
autocomplete_light/example_apps/autocomplete_test_case_app/models.py
autocomplete_light/example_apps/basic/__init__.py
autocomplete_light/example_apps/basic/admin.py
autocomplete_light/example_apps/basic/autocomplete_light_registry.py
autocomplete_light/example_apps/basic/forms.py
autocomplete_light/example_apps/basic/models.py
autocomplete_light/example_apps/basic/fixtures/basic_gfk_gmtm.json
autocomplete_light/example_apps/basic/fixtures/initial_data.json
autocomplete_light/example_apps/charfield_autocomplete/__init__.py
autocomplete_light/example_apps/charfield_autocomplete/admin.py
autocomplete_light/example_apps/charfield_autocomplete/autocomplete_light_registry.py
autocomplete_light/example_apps/charfield_autocomplete/forms.py
autocomplete_light/example_apps/charfield_autocomplete/models.py
autocomplete_light/example_apps/create_choice_on_the_fly/__init__.py
django_autocomplete_light_bsc.egg-info/PKG-INFO
django_autocomplete_light_bsc.egg-info/SOURCES.txt
django_autocomplete_light_bsc.egg-info/dependency_links.txt
django_autocomplete_light_bsc.egg-info/not-zip-safe
django_autocomplete_light_bsc.egg-info/requires.txt
django_autocomplete_light_bsc.egg-info/top_level.txt