Metadata-Version: 1.1
Name: django-autocomplete-light-bsc
Version: 2.0.0a18
Summary: Fresh autocompletes for Django
Home-page: http://django-autocomplete-light.rtfd.org
Author: James Pic
Author-email: jamespic@gmail.com
License: MIT
Keywords: django autocomplete
Platform: UNKNOWN
Classifier: Development Status :: 3 - Alpha
Classifier: Environment :: Web Environment
Classifier: Framework :: Django
Classifier: Intended Audience :: Developers
Classifier: License :: OSI Approved :: MIT License
Classifier: Operating System :: OS Independent
Classifier: Programming Language :: Python
Classifier: Programming Language :: Python :: 2
Classifier: Programming Language :: Python :: 3
Classifier: Topic :: Internet :: WWW/HTTP
Classifier: Topic :: Software Development :: Libraries :: Python Modules
